sjvisualizer/AreaChart.py
sjvisualizer/AreaPlot.py
sjvisualizer/Axis.py
sjvisualizer/BarRace.py
sjvisualizer/BarRace_legacy.py
sjvisualizer/Bubble.py
sjvisualizer/Canvas.py
sjvisualizer/DataHandler.py
sjvisualizer/Date.py
sjvisualizer/DynamicLine.py
sjvisualizer/DynamicMatrix.py
sjvisualizer/Empty.py
sjvisualizer/Histogram.py
sjvisualizer/Legend.py
sjvisualizer/LineChart.py
sjvisualizer/PieRace.py
sjvisualizer/StackedBarChart.py
sjvisualizer/StaticImage.py
sjvisualizer/StaticText.py
sjvisualizer/Total.py
sjvisualizer/WorldMap.py
sjvisualizer/XYLine.py
sjvisualizer/__init__.py
sjvisualizer/plot.py
sjvisualizer/world.json
sjvisualizer/assets/Made with SJvisualzer.png
sjvisualizer-0.0.15.dist-info/LICENSE
sjvisualizer-0.0.15.dist-info/METADATA
sjvisualizer-0.0.15.dist-info/WHEEL
sjvisualizer-0.0.15.dist-info/top_level.txt
sjvisualizer-0.0.15.dist-info/RECORD
