Metadata-Version: 2.1
Name: sjvisualizer
Version: 0.0.15
Summary: Package to animate your data
Home-page: https://www.sjdataviz.com/
Author: Sjoerd Tilmans
Author-email: info@sjdataviz.com
Classifier: Programming Language :: Python :: 3
Classifier: License :: OSI Approved :: MIT License
Classifier: Operating System :: OS Independent
Requires-Python: >=3.7
License-File: LICENSE
Requires-Dist: pandas (>=2.0)
Requires-Dist: screeninfo (>=0.7)
Requires-Dist: Pillow (>9)
Requires-Dist: openpyxl (>3)
Requires-Dist: opencv-python (>=4.8)
